LICENSE
sliced_prediction/__init__.py
sliced_prediction/sliced_prediction.py
sliced_prediction-0.0.7.dist-info/entry_points.txt
sliced_prediction-0.0.7.dist-info/LICENSE
sliced_prediction-0.0.7.dist-info/WHEEL
sliced_prediction-0.0.7.dist-info/METADATA
sliced_prediction-0.0.7.dist-info/RECORD
